MANIFEST.in
README
setup.py
pytracker/__init__.py
pytracker/trackable.c
pytracker/trackable.h
pytracker/tracker.py
pytracker.egg-info/PKG-INFO
pytracker.egg-info/SOURCES.txt
pytracker.egg-info/dependency_links.txt
pytracker.egg-info/top_level.txt