Metadata-Version: 1.1
Name: pytracker
Version: 1.0.2
Summary: Object tracking classes for efficient inventory of allocated/freed objects
Home-page: http://github.com/garywiz/pytracker
Author: Gary Wisniewski
Author-email: pypi-garywiz@gw.spidereye.com
License: BSD 3
Platform: UNKNOWN
Classifier: Development Status :: 4 - Beta
Classifier: Intended Audience :: Developers
Classifier: License :: OSI Approved :: BSD License
Classifier: Natural Language :: English
Classifier: Operating System :: POSIX :: Linux
Classifier: Programming Language :: Python
Classifier: Programming Language :: C
Classifier: Topic :: Software Development :: Libraries :: Python Modules
Classifier: Topic :: Software Development :: Quality Assurance
Classifier: Topic :: System :: Monitoring
